Metadata-Version: 2.1
Name: zigpy-xbee-homeassistant
Version: 0.11.0
Summary: A library which communicates with XBee radios for zigpy
Home-page: http://github.com/zigpy/zigpy-xbee
Author: Russell Cloran
Author-email: rcloran@gmail.com
License: GPL-3.0
Platform: UNKNOWN
Requires-Dist: pyserial-asyncio
Requires-Dist: zigpy-homeassistant (>=0.17.0)
